sphinx_inlinecode/__init__.py
sphinx_inlinecode/_static/sphinx-inlinecode.css
sphinx_inlinecode/_static/sphinx-inlinecode.js
sphinx_inlinecode-2.0.1.dist-info/LICENSE
sphinx_inlinecode-2.0.1.dist-info/METADATA
sphinx_inlinecode-2.0.1.dist-info/WHEEL
sphinx_inlinecode-2.0.1.dist-info/top_level.txt
sphinx_inlinecode-2.0.1.dist-info/RECORD
