Metadata-Version: 2.1
Name: sphinx-inlinecode
Version: 2.0.1
Summary: A Sphinx extension to embed source code blocks directly into documentation
Home-page: https://github.com/tdkorn/sphinx-inlinecode
Author: Adam Korn
Author-email: hello@dailykitten.net
License: MIT License
Download-URL: https://github.com/TDKorn/sphinx-inlinecode/tarball/main
Keywords: sphinx,viewcode,sphinx-extension,sphinx-contrib,code-block,inline-code,sphinx-ext,inline,embed,documentation
Platform: UNKNOWN
Classifier: Framework :: Sphinx :: Extension
Classifier: License :: OSI Approved :: MIT License
Classifier: Programming Language :: Python :: 3
Classifier: Programming Language :: Python :: 3.10
License-File: LICENSE
Requires-Dist: sphinx (>=1.8)
Requires-Dist: beautifulsoup4
